open_vad/__init__.py
open_vad/decoder.py
open_vad/encoder_block.py
open_vad/silero_vad.py
open_vad/stft.py
open_vad/utils.py
open_voice_activity_detection-0.0.2.dist-info/METADATA
open_voice_activity_detection-0.0.2.dist-info/WHEEL
open_voice_activity_detection-0.0.2.dist-info/licenses/LICENSE.txt
open_voice_activity_detection-0.0.2.dist-info/RECORD
