Metadata-Version: 2.4
Name: open-voice-activity-detection
Version: 0.0.2
Summary: Fully open-source and state-of-the-art Voice Activity Detection (VAD) models for academic research and commercial applications.
Project-URL: Homepage, https://github.com/stefanwebb/open-voice-activity-detection
Project-URL: Issues, https://github.com/stefanwebb/open-voice-activity-detection/issues
Author-email: Stefan Webb <info@stefanwebb.me>
License-Expression: CC-BY-SA-4.0
License-File: LICENSE.txt
Classifier: Operating System :: OS Independent
Classifier: Programming Language :: Python :: 3
Requires-Python: >=3.11
